telium/__init__.py
telium/constant.py
telium/hexdump.py
telium/manager.py
telium/payment.py
telium/version.py
pyTeliumManager-2.4.2.dist-info/LICENSE
pyTeliumManager-2.4.2.dist-info/METADATA
pyTeliumManager-2.4.2.dist-info/WHEEL
pyTeliumManager-2.4.2.dist-info/top_level.txt
pyTeliumManager-2.4.2.dist-info/RECORD
