Metadata-Version: 2.1
Name: pyTeliumManager
Version: 2.4.2
Summary: A cross-platform point of sales payment manager tool with Telium Manager Support every device with Telium Manager like Ingenico terminals.
Home-page: https://github.com/Ousret/pyTeliumManager
Author: Ahmed TAHRI, @Ousret
Author-email: ahmed.tahri@cloudnursery.dev
License: MIT
Keywords: ingenico,telium manager,telium,payment,credit card,debit card,visa,mastercard,merchant,pos
Platform: UNKNOWN
Classifier: Development Status :: 5 - Production/Stable
Classifier: Environment :: Win32 (MS Windows)
Classifier: Environment :: X11 Applications
Classifier: Environment :: MacOS X
Classifier: Intended Audience :: Developers
Classifier: License :: OSI Approved :: MIT License
Classifier: Operating System :: OS Independent
Classifier: Programming Language :: Python
Classifier: Programming Language :: Python :: 2.7
Classifier: Programming Language :: Python :: 3
Classifier: Programming Language :: Python :: 3.1
Classifier: Programming Language :: Python :: 3.2
Classifier: Programming Language :: Python :: 3.3
Classifier: Programming Language :: Python :: 3.4
Classifier: Programming Language :: Python :: 3.5
Classifier: Programming Language :: Python :: 3.6
Classifier: Programming Language :: Python :: 3.7
Classifier: Programming Language :: Python :: 3.8
Classifier: Programming Language :: Python :: 3.9
Classifier: Programming Language :: Python :: 3.10
License-File: LICENSE
Requires-Dist: pyserial (>=3.3)
Requires-Dist: pycountry (<18.5.20,>=17.0)
Requires-Dist: payment-card-identifier (>=0.1.2)
Requires-Dist: six
